{
	"format_version": "1.21.90",
	"minecraft:weighted_random_feature": {
		"description": {
			"identifier": "daniye:red_mushroom_weighted_random_feature"
		},
		"features": [
			[
				"daniye:red_mushroom_01_mcstructure",
				1
			],
			[
				"daniye:red_mushroom_02_mcstructure",
				1
			],
			[
				"daniye:red_mushroom_03_mcstructure",
				1
			],
			[
				"daniye:red_mushroom_04_mcstructure",
				1
			],
			[
				"daniye:red_mushroom_05_mcstructure",
				1
			],
			[
				"daniye:red_mushroom_06_mcstructure",
				1
			]
		]
	}
}