{
	"format_version": "1.12.0",
	"minecraft:geometry": [
		{
			"description": {
				"identifier": "geometry.villager_v2",
				"texture_width": 64,
				"texture_height": 64,
				"visible_bounds_width": 2,
				"visible_bounds_height": 3,
				"visible_bounds_offset": [0, 1.5, 0]
			},
			"bones": [
				{
					"name": "body",
					"pivot": [0, 0, 0],
					"cubes": [
						{"origin": [-4, 12, -3], "size": [8, 12, 6], "uv": [16, 20]},
						{"origin": [-4, 4, -3], "size": [8, 20, 6], "inflate": 0.5, "uv": [0, 38]}
					],
					"locators": {
						"lead_hold": [0, 40, 0]
					}
				},
				{
					"name": "head",
					"parent": "body",
					"pivot": [0, 24, 0],
					"cubes": [
						{"origin": [-4, 24, -4], "size": [8, 10, 8], "uv": [0, 0]},
						{
							"origin": [-4.5, 29.5, -5.9],
							"size": [9, 0.5, 10],
							"uv": {
								"north": {"uv": [5.4, 0], "uv_size": [0.4, 0.7]},
								"east": {"uv": [5.3, 0], "uv_size": [0.36667, 0.63333]},
								"south": {"uv": [5.3, 0], "uv_size": [0.3, 0.63333]},
								"west": {"uv": [5.3, 0], "uv_size": [0.43333, 0.66667]},
								"up": {"uv": [5.2, 0.03333], "uv_size": [0.6, 0.66667]},
								"down": {"uv": [5.5, 0.86667], "uv_size": [0.3, -0.86667]}
							}
						},
						{
							"origin": [-0.5, 34, -0.5],
							"size": [1, 2.5, 1],
							"uv": {
								"north": {"uv": [3.46667, 0], "uv_size": [0.4, 0.7]},
								"east": {"uv": [3.36667, 0], "uv_size": [0.36667, 0.63333]},
								"south": {"uv": [3.36667, 0], "uv_size": [0.3, 0.63333]},
								"west": {"uv": [3.36667, 0], "uv_size": [0.43333, 0.66667]},
								"up": {"uv": [3.26667, 0.03333], "uv_size": [0.6, 0.66667]},
								"down": {"uv": [3.56667, 0.86667], "uv_size": [0.3, -0.86667]}
							}
						},
						{
							"origin": [-0.5, 36.5, -2.5],
							"size": [1, 0.5, 5],
							"pivot": [0, 36.75, 0],
							"rotation": [0, 45, 0],
							"uv": {
								"north": {"uv": [4.43333, 0], "uv_size": [0.4, 0.7]},
								"east": {"uv": [4.33333, 0], "uv_size": [0.36667, 0.63333]},
								"south": {"uv": [4.33333, 0], "uv_size": [0.3, 0.63333]},
								"west": {"uv": [4.33333, 0], "uv_size": [0.43333, 0.66667]},
								"up": {"uv": [4.23333, 0.03333], "uv_size": [0.6, 0.66667]},
								"down": {"uv": [4.53333, 0.86667], "uv_size": [0.3, -0.86667]}
							}
						},
						{
							"origin": [-2.5, 36.5, -0.5],
							"size": [5, 0.5, 1],
							"pivot": [0, 36.75, 0],
							"rotation": [0, 45, 0],
							"uv": {
								"north": {"uv": [4.43333, 0], "uv_size": [0.4, 0.7]},
								"east": {"uv": [4.33333, 0], "uv_size": [0.36667, 0.63333]},
								"south": {"uv": [4.33333, 0], "uv_size": [0.3, 0.63333]},
								"west": {"uv": [4.33333, 0], "uv_size": [0.43333, 0.66667]},
								"up": {"uv": [4.23333, 0.03333], "uv_size": [0.6, 0.66667]},
								"down": {"uv": [4.53333, 0.86667], "uv_size": [0.3, -0.86667]}
							}
						},
						{
							"origin": [-4, 30.1, -4],
							"size": [8, 4.5, 8],
							"inflate": 0.1,
							"uv": {
								"north": {"uv": [0, 0], "uv_size": [2.96667, 1]},
								"east": {"uv": [0.23333, 0.2], "uv_size": [0.36667, 0.63333]},
								"south": {"uv": [3, 0], "uv_size": [-3, 0.9]},
								"west": {"uv": [2.43333, 0.06667], "uv_size": [0.43333, 0.66667]},
								"up": {"uv": [0, 0], "uv_size": [3, 1]},
								"down": {"uv": [5.5, 0.86667], "uv_size": [0.3, -0.86667]}
							}
						}
					]
				},
				{
					"name": "helmet",
					"parent": "head",
					"pivot": [0, 24, 0],
					"cubes": [
						{"origin": [-4, 24, -4], "size": [8, 10, 8], "inflate": 0.51, "uv": [32, 0]}
					]
				},
				{
					"name": "brim",
					"parent": "head",
					"pivot": [0, 24, 0],
					"cubes": [
						{"origin": [-8, 16, -6], "size": [16, 16, 1], "uv": [30, 47]}
					]
				},
				{
					"name": "nose",
					"parent": "head",
					"pivot": [0, 26, 0],
					"cubes": [
						{"origin": [-1, 23, -6], "size": [2, 4, 2], "uv": [24, 0]}
					]
				},
				{
					"name": "arms",
					"parent": "body",
					"pivot": [0, 22, 0],
					"cubes": [
						{"origin": [-4, 16, -2], "size": [8, 4, 4], "uv": [40, 38]},
						{"origin": [-8, 16, -2], "size": [4, 8, 4], "uv": [44, 22]},
						{"origin": [4, 16, -2], "size": [4, 8, 4], "uv": [44, 22], "mirror": true}
					]
				},
				{
					"name": "held_item",
					"parent": "arms",
					"pivot": [0, 0, 0]
				},
				{
					"name": "leg0",
					"parent": "body",
					"pivot": [-2, 12, 0],
					"cubes": [
						{"origin": [-4, 0, -2], "size": [4, 12, 4], "uv": [0, 22]}
					]
				},
				{
					"name": "leg1",
					"parent": "body",
					"pivot": [2, 12, 0],
					"cubes": [
						{"origin": [0, 0, -2], "size": [4, 12, 4], "uv": [0, 22], "mirror": true}
					]
				}
			]
		}
	]
}