{
	"format_version": "1.8.0",
	"animations": {
		"animation.greymatter_fp": {
			"loop": true,
			"animation_length": 2,
			"bones": {
				"fp": {
					"scale": 1.6,
					"rotation": {
						"0.0": [
							2.5,
							0,
							0
						],
						"0.75": [
							-2.5,
							0,
							0
						],
						"1.5": [
							2.5,
							0,
							0
						]
					}
				},
				"arm1": {
					"rotation": {
						"0.0": [
							0,
							0,
							0
						],
						"1.0": [
							0,
							0,
							5
						],
						"2.0": [
							0,
							0,
							0
						]
					}
				},
				"fg1": {
					"rotation": {
						"0.0": [
							0,
							0,
							0
						],
						"1.0": [
							0,
							0,
							-15
						],
						"2.0": [
							0,
							0,
							0
						]
					}
				},
				"fg2": {
					"rotation": {
						"0.0": [
							0,
							0,
							0
						],
						"1.0": [
							0,
							0,
							10
						],
						"2.0": [
							0,
							0,
							0
						]
					}
				},
				"fg3": {
					"rotation": {
						"0.0": [
							0,
							0,
							0
						],
						"1.0": [
							0,
							0,
							10
						],
						"2.0": [
							0,
							0,
							0
						]
					}
				},
				"fg4": {
					"rotation": {
						"0.0": [
							0,
							0,
							0
						],
						"1.0": [
							0,
							0,
							10
						],
						"2.0": [
							0,
							0,
							0
						]
					}
				},
				"arm2": {
					"rotation": {
						"0.0": [
							0,
							0,
							0
						],
						"1.0": [
							0,
							0,
							-5
						],
						"2.0": [
							0,
							0,
							0
						]
					}
				},
				"fg5": {
					"rotation": {
						"0.0": [
							0,
							0,
							0
						],
						"1.0": [
							0,
							0,
							15
						],
						"2.0": [
							0,
							0,
							0
						]
					}
				},
				"fg6": {
					"rotation": {
						"0.0": [
							0,
							0,
							0
						],
						"1.0": [
							0,
							0,
							-10
						],
						"2.0": [
							0,
							0,
							0
						]
					}
				},
				"fg7": {
					"rotation": {
						"0.0": [
							0,
							0,
							0
						],
						"1.0": [
							0,
							0,
							-10
						],
						"2.0": [
							0,
							0,
							0
						]
					}
				},
				"fg8": {
					"rotation": {
						"0.0": [
							0,
							0,
							0
						],
						"1.0": [
							0,
							0,
							-10
						],
						"2.0": [
							0,
							0,
							0
						]
					}
				}
			}
		},
		"animation.greymatter_idle": {
			"loop": true,
			"animation_length": 2,
			"bones": {
				"arm1": {
					"rotation": {
						"0.0": [
							0,
							0,
							0
						],
						"1.0": [
							0,
							0,
							5
						],
						"2.0": [
							0,
							0,
							0
						]
					}
				},
				"fg1": {
					"rotation": {
						"0.0": [
							0,
							0,
							0
						],
						"1.0": [
							0,
							0,
							-15
						],
						"2.0": [
							0,
							0,
							0
						]
					}
				},
				"fg2": {
					"rotation": {
						"0.0": [
							0,
							0,
							0
						],
						"1.0": [
							0,
							0,
							10
						],
						"2.0": [
							0,
							0,
							0
						]
					}
				},
				"fg3": {
					"rotation": {
						"0.0": [
							0,
							0,
							0
						],
						"1.0": [
							0,
							0,
							10
						],
						"2.0": [
							0,
							0,
							0
						]
					}
				},
				"fg4": {
					"rotation": {
						"0.0": [
							0,
							0,
							0
						],
						"1.0": [
							0,
							0,
							10
						],
						"2.0": [
							0,
							0,
							0
						]
					}
				},
				"arm2": {
					"rotation": {
						"0.0": [
							0,
							0,
							0
						],
						"1.0": [
							0,
							0,
							-5
						],
						"2.0": [
							0,
							0,
							0
						]
					}
				},
				"fg5": {
					"rotation": {
						"0.0": [
							0,
							0,
							0
						],
						"1.0": [
							0,
							0,
							15
						],
						"2.0": [
							0,
							0,
							0
						]
					}
				},
				"fg6": {
					"rotation": {
						"0.0": [
							0,
							0,
							0
						],
						"1.0": [
							0,
							0,
							-10
						],
						"2.0": [
							0,
							0,
							0
						]
					}
				},
				"fg7": {
					"rotation": {
						"0.0": [
							0,
							0,
							0
						],
						"1.0": [
							0,
							0,
							-10
						],
						"2.0": [
							0,
							0,
							0
						]
					}
				},
				"fg8": {
					"rotation": {
						"0.0": [
							0,
							0,
							0
						],
						"1.0": [
							0,
							0,
							-10
						],
						"2.0": [
							0,
							0,
							0
						]
					}
				}
			}
		},
		"animation.greymatter_sneaking": {
			"loop": true,
			"animation_length": 0.5,
			"bones": {
				"fullbody": {
					"position": [
						0,
						-2,
						0
					]
				},
				"upperbody": {
					"rotation": [
						25,
						0,
						0
					]
				},
				"arm1": {
					"rotation": [
						0,
						0,
						7.5
					]
				},
				"arm1_p2": {
					"rotation": [
						-67.09019,
						-10.28859,
						22.90981
					]
				},
				"arm2": {
					"rotation": [
						0.12112,
						-4.64268,
						-5.89557
					]
				},
				"arm2_p2": {
					"rotation": [
						-67.09019,
						10.28859,
						-22.90981
					]
				},
				"leg1": {
					"rotation": [
						-52.5,
						0,
						0
					]
				},
				"leg1_p2": {
					"rotation": [
						60,
						0,
						0
					]
				},
				"leg1_p3": {
					"rotation": [
						-5,
						0,
						0
					]
				},
				"leg2": {
					"rotation": [
						15,
						0,
						0
					]
				},
				"leg2_p2": {
					"rotation": [
						65,
						0,
						0
					]
				},
				"leg2_p3": {
					"rotation": [
						-45,
						0,
						0
					]
				}
			}
		},
		"animation.greymatter_jumping": {
			"loop": true,
			"animation_length": 0.5,
			"bones": {
				"fullbody": {
					"position": [
						0,
						2,
						-1
					]
				},
				"upperbody": {
					"rotation": [
						15,
						0,
						0
					]
				},
				"arm1": {
					"rotation": [
						22.32648,
						-2.86313,
						6.93488
					]
				},
				"arm1_p2": {
					"rotation": [
						-40,
						0,
						0
					]
				},
				"arm2": {
					"rotation": [
						22.32648,
						2.86313,
						-6.93488
					]
				},
				"arm2_p2": {
					"rotation": [
						-40,
						0,
						0
					]
				},
				"leg1": {
					"rotation": [
						-14.94548,
						1.29256,
						4.83045
					]
				},
				"leg1_p2": {
					"rotation": [
						55,
						0,
						0
					]
				},
				"leg2": {
					"rotation": [
						-14.94548,
						-1.29256,
						-4.83045
					]
				},
				"leg2_p2": {
					"rotation": [
						55,
						0,
						0
					]
				}
			}
		},
		"animation.greymatter_attacking": {
			"loop": true,
			"animation_length": 0.5,
			"override_previous_animation": true,
			"bones": {
				"upperbody": {
					"rotation": {
						"0.0": [
							0,
							7.5,
							0
						],
						"0.2083": [
							7.5,
							-10,
							0
						]
					}
				},
				"arm1": {
					"rotation": {
						"0.0": [
							26.40319,
							-7.98133,
							15.62489
						],
						"0.1667": [
							-63.59681,
							-7.98133,
							15.62489
						]
					}
				},
				"arm1_p2": {
					"rotation": {
						"0.0": [
							-90,
							0,
							47.5
						],
						"0.1667": [
							-51.87366,
							-46.91981,
							42.94218
						]
					}
				},
				"fg1": {
					"rotation": [
						-12.5,
						0,
						-10
					]
				},
				"fg1_p2": {
					"rotation": [
						0,
						0,
						42.5
					]
				},
				"fg2": {
					"rotation": [
						0,
						0,
						-2.5
					]
				},
				"fg2_p2": {
					"rotation": [
						0,
						0,
						-35
					]
				},
				"fg3": {
					"rotation": [
						0,
						0,
						-2.5
					]
				},
				"fg3_p2": {
					"rotation": [
						0,
						0,
						-35
					]
				},
				"fg4": {
					"rotation": [
						0,
						0,
						-2.5
					]
				},
				"fg4_p2": {
					"rotation": [
						0,
						0,
						-35
					]
				},
				"arm2": {
					"rotation": [
						14.94548,
						1.29256,
						-4.83045
					]
				},
				"arm2_p2": {
					"rotation": [
						-30,
						0,
						0
					]
				}
			}
		},
		"animation.greymatter_moving": {
			"loop": true,
			"animation_length": 0.5,
			"bones": {
				"arm1": {
					"rotation": {
						"0.0": [
							35,
							0,
							0
						],
						"0.25": [
							-22.5,
							0,
							0
						],
						"0.5": [
							35,
							0,
							0
						]
					}
				},
				"arm1_p2": {
					"rotation": {
						"0.0": [
							-35,
							0,
							0
						],
						"0.5": [
							-35,
							0,
							0
						]
					}
				},
				"arm2": {
					"rotation": {
						"0.0": [
							-22.5,
							0,
							0
						],
						"0.25": [
							35,
							0,
							0
						],
						"0.5": [
							-22.5,
							0,
							0
						]
					}
				},
				"arm2_p2": {
					"rotation": {
						"0.0": [
							-35,
							0,
							0
						],
						"0.5": [
							-35,
							0,
							0
						]
					}
				},
				"leg1": {
					"rotation": {
						"0.0": [
							-47.5,
							0,
							0
						],
						"0.25": [
							25,
							0,
							0
						],
						"0.5": [
							-47.5,
							0,
							0
						]
					}
				},
				"leg1_p2": {
					"rotation": {
						"0.0": [
							32.5,
							0,
							0
						],
						"0.5": [
							32.5,
							0,
							0
						]
					}
				},
				"leg1_p3": {
					"rotation": [
						-25,
						0,
						0
					]
				},
				"leg2": {
					"rotation": {
						"0.0": [
							25,
							0,
							0
						],
						"0.25": [
							-47.5,
							0,
							0
						],
						"0.5": [
							25,
							0,
							0
						]
					}
				},
				"leg2_p2": {
					"rotation": [
						32.5,
						0,
						0
					]
				},
				"leg2_p3": {
					"rotation": {
						"0.0": [
							-25,
							0,
							0
						],
						"0.5": [
							-25,
							0,
							0
						]
					}
				}
			}
		},
		"animation.greymatter_swimming": {
			"loop": true,
			"animation_length": 1,
			"bones": {
				"fullbody": {
					"rotation": [
						90,
						0,
						0
					],
					"position": [
						0,
						-8,
						-2
					]
				},
				"upperbody": {
					"rotation": [
						-15,
						0,
						0
					]
				},
				"head2": {
					"rotation": [
						-75,
						0,
						0
					]
				},
				"arm1": {
					"rotation": {
						"0.0": [
							-120,
							0,
							0
						],
						"0.5": [
							-60,
							0,
							0
						],
						"1.0": [
							-120,
							0,
							0
						]
					}
				},
				"arm2": {
					"rotation": {
						"0.0": [
							-60,
							0,
							0
						],
						"0.5": [
							-120,
							0,
							0
						],
						"1.0": [
							-60,
							0,
							0
						]
					}
				},
				"leg1": {
					"rotation": {
						"0.0": [
							-20,
							0,
							0
						],
						"0.5": [
							20,
							0,
							0
						],
						"1.0": [
							-20,
							0,
							0
						]
					}
				},
				"leg1_p2": {
					"rotation": [
						20,
						0,
						0
					]
				},
				"leg2": {
					"rotation": {
						"0.0": [
							20,
							0,
							0
						],
						"0.5": [
							-20,
							0,
							0
						],
						"1.0": [
							20,
							0,
							0
						]
					}
				},
				"leg2_p2": {
					"rotation": [
						20,
						0,
						0
					]
				}
			}
		}
	}
}